lucianosyllvaPackageOne/__init__.py
lucianosyllvaPackageOne/add.py
lucianosyllvaPackageOne/subtract.py
lucianosyllvaPackageOne/extras/__init__.py
lucianosyllvaPackageOne/extras/divide.py
lucianosyllvaPackageOne/extras/multiply.py
lucianosyllvaPackageOne-0.0.1.dist-info/METADATA
lucianosyllvaPackageOne-0.0.1.dist-info/WHEEL
lucianosyllvaPackageOne-0.0.1.dist-info/top_level.txt
lucianosyllvaPackageOne-0.0.1.dist-info/RECORD
