Metadata-Version: 2.1
Name: lucianosyllvaPackageOne
Version: 0.0.1
Summary: Meu primeiro pacote em Python
Author: Luciano Syllva
Author-email: <lucianosyllva@gmail.com>
Keywords: python,first package
Classifier: Development Status :: 3 - Alpha
Classifier: Intended Audience :: Education
Classifier: Programming Language :: Python :: 2
Classifier: Programming Language :: Python :: 3
Classifier: Operating System :: MacOS :: MacOS X
Classifier: Operating System :: Microsoft :: Windows
